tipe/__init__.py
tipe/py.typed
tipe/tipe.py
tipe-1.1.0.dist-info/LICENSE
tipe-1.1.0.dist-info/METADATA
tipe-1.1.0.dist-info/WHEEL
tipe-1.1.0.dist-info/RECORD
