Metadata-Version: 2.1
Name: tipe
Version: 1.1.0
Summary: Typed pipe
Author: Denis Mishankov
Author-email: mishankov@mail.com
Requires-Python: >=3.8,<4.0
Classifier: Programming Language :: Python :: 3
Classifier: Programming Language :: Python :: 3.8
Classifier: Programming Language :: Python :: 3.9
Classifier: Programming Language :: Python :: 3.10
Classifier: Programming Language :: Python :: 3.11
Classifier: Programming Language :: Python :: 3.12
